sageai/__init__.py
sageai/config.py
sageai/sageai.py
sageai/services/defaultvectordb_service.py
sageai/services/openai_service.py
sageai/tests/integration.py
sageai/tests/main.py
sageai/tests/unit.py
sageai/tests/utils.py
sageai/types/abstract_vectordb.py
sageai/types/function.py
sageai/types/log_level.py
sageai/utils/file_utilities.py
sageai/utils/format_config_args.py
sageai/utils/inspection_utilities.py
sageai/utils/logger.py
sageai/utils/model_utilities.py
sageai/utils/openai_utilities.py
sageai-1.0.5.dist-info/LICENSE
sageai-1.0.5.dist-info/METADATA
sageai-1.0.5.dist-info/WHEEL
sageai-1.0.5.dist-info/entry_points.txt
sageai-1.0.5.dist-info/RECORD
