Metadata-Version: 2.1
Name: sageai
Version: 1.0.5
Summary: File-based functions for ChatGPT's function calling with Pydantic support
License: MIT
Keywords: python,openai,functions,chatgpt,gpt4,genai,function-calling
Author: JUNIORCO
Author-email: sami@lasso.gg
Requires-Python: >=3.9,<3.12
Classifier: License :: OSI Approved :: MIT License
Classifier: Programming Language :: Python :: 3
Classifier: Programming Language :: Python :: 3.9
Classifier: Programming Language :: Python :: 3.10
Classifier: Programming Language :: Python :: 3.11
Requires-Dist: openai (>=1.2.0)
Requires-Dist: pydantic (>=1.6,<=1.10.12)
Requires-Dist: qdrant-client (>=1.4.0)
